LICENSE
MANIFEST.in
README.rst
setup.cfg
setup.py
versioneer.py
aehmc/__init__.py
aehmc/_version.py
aehmc/algorithms.py
aehmc/hmc.py
aehmc/integrators.py
aehmc/mass_matrix.py
aehmc/metrics.py
aehmc/nuts.py
aehmc/proposals.py
aehmc/step_size.py
aehmc/termination.py
aehmc/trajectory.py
aehmc/utils.py
aehmc/window_adaptation.py
aehmc.egg-info/PKG-INFO
aehmc.egg-info/SOURCES.txt
aehmc.egg-info/dependency_links.txt
aehmc.egg-info/not-zip-safe
aehmc.egg-info/requires.txt
aehmc.egg-info/top_level.txt